slip39/__init__.py
slip39/__main__.py
slip39/api.py
slip39/api_passphrase_test.py
slip39/api_test.py
slip39/communications.py
slip39/communications_test.py
slip39/defaults.py
slip39/dependency_test.py
slip39/exceptions.py
slip39/generator_test.py
slip39/limits.py
slip39/limits_test.py
slip39/main.py
slip39/output_test.py
slip39/payments.py
slip39/payments_test.py
slip39/recovery_test.py
slip39/util.py
slip39/util_test.py
slip39/version.py
slip39/cli/__init__.py
slip39/cli/__main__.py
slip39/generator/__init__.py
slip39/generator/__main__.py
slip39/generator/main.py
slip39/gui/SLIP-39-ANONYMOUS.txt
slip39/gui/SLIP-39-AS-BIP.txt
slip39/gui/SLIP-39-CRYPTO.txt
slip39/gui/SLIP-39-CS.txt
slip39/gui/SLIP-39-EXTENDABLE.txt
slip39/gui/SLIP-39-G-NAME.txt
slip39/gui/SLIP-39-G.txt
slip39/gui/SLIP-39-LO.txt
slip39/gui/SLIP-39-PASSPHRASE.txt
slip39/gui/SLIP-39-PF.txt
slip39/gui/SLIP-39-SD.txt
slip39/gui/SLIP-39-SE-SIGS.txt
slip39/gui/SLIP-39-SE.txt
slip39/gui/SLIP-39-THRESHOLD.txt
slip39/gui/SLIP-39-WALLET.txt
slip39/gui/SLIP-39.txt
slip39/gui/__init__.py
slip39/gui/__main__.py
slip39/gui/main.py
slip39/invoice/Tokens.py
slip39/invoice/__init__.py
slip39/invoice/artifact.py
slip39/invoice/artifact_test.py
slip39/invoice/bitquery_test.py
slip39/invoice/ethereum.py
slip39/invoice/ethereum_test.py
slip39/invoice/multipayout.py
slip39/invoice/multipayout_test.py
slip39/layout/1x1-ffffff3f.png
slip39/layout/1x1-ffffff54.png
slip39/layout/1x1-ffffffbf.png
slip39/layout/BNB.png
slip39/layout/BTC.png
slip39/layout/COVER-BIP-39.txt
slip39/layout/COVER-SLIP-39.txt
slip39/layout/COVER.txt
slip39/layout/CRO.png
slip39/layout/DOGE.png
slip39/layout/ETH.png
slip39/layout/LTC.png
slip39/layout/SLIP-39.png
slip39/layout/XRP.png
slip39/layout/__init__.py
slip39/layout/components.py
slip39/layout/paper-wallet-background.png
slip39/layout/pdf.py
slip39/layout/printer.py
slip39/layout/font/DejaVuSansMono-Bold.ttf
slip39/layout/font/DejaVuSansMono-BoldOblique.ttf
slip39-14.1.0.dist-info/licenses/COPYING
slip39-14.1.0.dist-info/licenses/LICENSE
slip39-14.1.0.dist-info/METADATA
slip39-14.1.0.dist-info/WHEEL
slip39-14.1.0.dist-info/entry_points.txt
slip39-14.1.0.dist-info/top_level.txt
slip39-14.1.0.dist-info/zip-safe
slip39-14.1.0.dist-info/RECORD
