Metadata-Version: 2.4
Name: slip39
Version: 14.1.0
Summary: Standards-compliant SLIP-39 cryptocurrency seed generation and recovery, compatible with Trezor hardware wallets
Author-email: Perry Kundert <perry@dominionrnd.com>
License-Expression: GPL-3.0-or-later OR LicenseRef-Proprietary
Project-URL: Bug Tracker, https://github.com/pjkundert/python-slip39/issues
Project-URL: Homepage, https://github.com/pjkundert/python-slip39
Keywords: Ethereum,Bitcoin,Dogecoin,Litecoin,cryptocurrency,SLIP-39,BIP-39,seed,recovery,PDF,BIP-38,paper,wallet
Classifier: Programming Language :: Python :: 3
Classifier: Development Status :: 5 - Production/Stable
Classifier: Intended Audience :: Developers
Classifier: Intended Audience :: Financial and Insurance Industry
Classifier: Environment :: Console
Classifier: Topic :: Security :: Cryptography
Classifier: Topic :: Office/Business :: Financial
Requires-Python: >=3.9
License-File: LICENSE
License-File: COPYING
Requires-Dist: base58<3,>=2.0.1
Requires-Dist: chacha20poly1305>=0.0.3
Requires-Dist: click<9,>=8.1.3
Requires-Dist: crypto-licensing<6,>=5.2.3
Requires-Dist: fpdf2<3,>=2.7.6
Requires-Dist: shamir-mnemonic-slip39<0.5,>=0.4.0
Requires-Dist: hdwallet-slip39<5,>=4.0.3
Requires-Dist: tabulate-slip39>=0.10.6
Requires-Dist: mnemonic<1,>=0.21
Requires-Dist: qrcode>=7.3
Provides-Extra: gui
Requires-Dist: FreeSimpleGUI<6,>=5.2; extra == "gui"
Provides-Extra: serial
Requires-Dist: pyserial>=3.5; extra == "serial"
Provides-Extra: wallet
Requires-Dist: eth-account<0.12,>=0.11.3; extra == "wallet"
Provides-Extra: invoice
Requires-Dist: eth-account<0.12,>=0.11.3; extra == "invoice"
Requires-Dist: py-solc-x<1.2,>=1.1.1; extra == "invoice"
Requires-Dist: pycryptodome<4,>=3.16; extra == "invoice"
Requires-Dist: requests<3,>=2.20; extra == "invoice"
Requires-Dist: dkimpy[ed25519]<2,>=1.0.5; extra == "invoice"
Requires-Dist: web3[tester]==6.20.4; extra == "invoice"
Requires-Dist: eth-tester[py-evm]<0.12.0b1,>=0.11.0b1; extra == "invoice"
Requires-Dist: py-geth<4,>=3.14.0; extra == "invoice"
Provides-Extra: tests
Requires-Dist: aiosmtpd<2,>=1.4; extra == "tests"
Requires-Dist: numpy; extra == "tests"
Requires-Dist: flake8; extra == "tests"
Requires-Dist: pytest; extra == "tests"
Requires-Dist: pytest-cov; extra == "tests"
Provides-Extra: dev
Requires-Dist: build; extra == "dev"
Requires-Dist: setuptools; extra == "dev"
Requires-Dist: wheel; extra == "dev"
Requires-Dist: pyinstaller>=6.17; extra == "dev"
Requires-Dist: tzdata; extra == "dev"
Dynamic: license-file
